defity-0.7.0.dist-info/METADATA
defity-0.7.0.dist-info/WHEEL
defity-0.7.0.dist-info/licenses/LICENSE
defity.libs/libgcc_s-98a1ef30.so.1
defity/__init__.py
defity/defity.cpython-314t-x86_64-linux-musl.so
defity/py.typed
defity-0.7.0.dist-info/RECORD
