Metadata-Version: 2.4
Name: defity
Version: 0.7.0
Classifier: Development Status :: 4 - Beta
Classifier: Intended Audience :: Developers
Classifier: Programming Language :: Python
Classifier: Programming Language :: Rust
Classifier: Operating System :: POSIX :: Linux
Classifier: License :: OSI Approved :: Apache Software License
License-File: LICENSE
Summary: Speedy library to detect file type from initial part of file content
Home-Page: https://github.com/hongquan/Defity
Author-email: Nguyễn Hồng Quân <ng.hong.quan@gmail.com>
Requires-Python: >=3.10
